gresit/__init__.py
gresit/background_knowledge.py
gresit/graphs.py
gresit/group_grandag.py
gresit/group_lingam.py
gresit/group_pc.py
gresit/group_random_regress.py
gresit/group_resit.py
gresit/independence_tests.py
gresit/learn_algorithms.py
gresit/losses.py
gresit/model_selection.py
gresit/params.py
gresit/regression_techniques.py
gresit/simulation_utils.py
gresit/synthetic_data.py
gresit/torch_models.py
gresit-1.0.0.dist-info/licenses/LICENSE.txt
gresit-1.0.0.dist-info/METADATA
gresit-1.0.0.dist-info/WHEEL
gresit-1.0.0.dist-info/top_level.txt
gresit-1.0.0.dist-info/RECORD
