Metadata-Version: 2.4
Name: gresit
Version: 1.0.0
Summary: Collection of methods and tools to learn causal graphs from grouped data.
Author-email: Konstantin Göbler <konstantin.goebler@tum.de>, Tobias Windisch <tobias.windisch@hs-kempten.de>, Mathias Drton <mathias.drton@tum.de>
Maintainer-email: Martin Roth <martin.roth2@bosch.com>
License: AGPL v3
Requires-Python: >3.10.0
License-File: LICENSE.txt
Requires-Dist: numpy<2
Requires-Dist: pandas
Requires-Dist: scikit-learn
Requires-Dist: statsmodels
Requires-Dist: plotly
Requires-Dist: xgboost
Requires-Dist: torch
Requires-Dist: seaborn
Requires-Dist: pyspark
Requires-Dist: scikit-misc
Requires-Dist: gadjid
Requires-Dist: tqdm
Requires-Dist: dcor
Requires-Dist: llvmlite==0.43.0
Requires-Dist: causal-learn
Requires-Dist: gcastle
Requires-Dist: gpytorch
Provides-Extra: dev
Requires-Dist: mike; extra == "dev"
Requires-Dist: mkdocs; extra == "dev"
Requires-Dist: mkdocs-material; extra == "dev"
Requires-Dist: mkdocstrings[python]; extra == "dev"
Requires-Dist: pip-licenses; extra == "dev"
Requires-Dist: pip-tools; extra == "dev"
Requires-Dist: pre-commit; extra == "dev"
Requires-Dist: pytest; extra == "dev"
Requires-Dist: pytest-cov; extra == "dev"
Requires-Dist: ruff; extra == "dev"
Requires-Dist: uv; extra == "dev"
Dynamic: license-file
